kernex/__init__.py
kernex/_src/__init__.py
kernex/_src/map.py
kernex/_src/scan.py
kernex/_src/utils.py
kernex/interface/__init__.py
kernex/interface/kernel_interface.py
kernex/interface/named_axis.py
kernex/interface/resolve_utils.py
kernex-0.2.1.dist-info/licenses/LICENSE
tests/__init__.py
tests/test_interface.py
tests/test_scan_and_map.py
tests/test_utils.py
tests_and_benchmarks/__init__.py
tests_and_benchmarks/test_benchmark_conv2d.py
tests_and_benchmarks/test_benchmark_patch.py
kernex-0.2.1.dist-info/METADATA
kernex-0.2.1.dist-info/WHEEL
kernex-0.2.1.dist-info/top_level.txt
kernex-0.2.1.dist-info/RECORD
